rispy/__init__.py
rispy/config.py
rispy/parser.py
rispy/utils.py
rispy/writer.py
rispy-0.8.1.dist-info/LICENSE
rispy-0.8.1.dist-info/WHEEL
rispy-0.8.1.dist-info/METADATA
rispy-0.8.1.dist-info/RECORD
