Metadata-Version: 2.1
Name: rispy
Version: 0.8.1
Summary: A Python reader/writer of RIS reference files
Keywords: RIS,parser,bibliograph
Author-email: Maik Derstappen <md@derico.de>
Maintainer-email: Andy Shapiro <shapiromatron@gmail.com>
Requires-Python: >=3.8
Classifier: Intended Audience :: Developers
Classifier: License :: OSI Approved :: MIT License
Classifier: Programming Language :: Python :: 3
Classifier: Programming Language :: Python :: 3.8
Classifier: Programming Language :: Python :: 3.9
Classifier: Programming Language :: Python :: 3.10
Classifier: Programming Language :: Python :: 3.11
Requires-Dist: pytest ~=7.4.0 ; extra == "dev"
Requires-Dist: flit ~= 3.9.0 ; extra == "dev"
Requires-Dist: black ~= 23.7.0 ; extra == "dev"
Requires-Dist: ruff ~= 0.0.278 ; extra == "dev"
Requires-Dist: coverage ~= 7.2.7 ; extra == "dev"
Project-URL: Source, https://github.com/mrtango/rispy
Provides-Extra: dev
